{
  "interval": 60000,
  "priceAggregator": "median",
  "defaultSource": [
    "binanceusdm"
  ],
  "sourceTimeout": 50000,
  "maxPriceDeviationPercent": 25,
  "evmChainId": 1,
  "tokens": {
    "SAND": {},
    "ZRX": {},
    "XRP": {},
    "TRX": {},
    "THETA": {},
    "ETC": {},
    "SRM": {},
    "CVC": {},
    "AKRO": {},
    "XLM": {},
    "UNI": {},
    "FIL": {},
    "MATIC": {},
    "DOGE": {},
    "LINK": {},
    "ENJ": {},
    "EOS": {},
    "AAVE": {},
    "BAND": {},
    "ZEC": {},
    "BAT": {},
    "KSM": {},
    "MANA": {},
    "VET": {},
    "YFI": {},
    "DOT": {},
    "BCH": {},
    "AXS": {},
    "BNB": {},
    "ETH": {},
    "NEO": {},
    "CHZ": {},
    "ADA": {},
    "QTUM": {},
    "BTC": {},
    "SOL": {},
    "BTT": {},
    "ZIL": {},
    "COMP": {},
    "LTC": {},
    "MKR": {},
    "SNX": {},
    "REEF": {},
    "OMG": {},
    "DASH": {},
    "XMR": {},
    "IOTA": {},
    "ONT": {},
    "IOST": {},
    "XEM": {},
    "REN": {},
    "ALGO": {},
    "ICX": {},
    "LRC": {},
    "YFII": {},
    "STORJ": {},
    "SUSHI": {},
    "CRV": {},
    "BLZ": {},
    "SC": {},
    "AVAX": {},
    "FLM": {},
    "NEAR": {},
    "ZEN": {},
    "GRT": {},
    "1INCH": {},
    "DODO": {},
    "NKN": {},
    "ALICE": {},
    "ICP": {},
    "CHR": {},
    "BAKE": {},
    "RUNE": {},
    "GTC": {},
    "KEEP": {},
    "RLC": {},
    "TLM": {},
    "ATOM": {},
    "KAVA": {},
    "RVN": {},
    "LINA": {},
    "EGLD": {},
    "FTM": {},
    "COTI": {},
    "XTZ": {},
    "ONE": {},
    "CELR": {},
    "ANKR": {},
    "HBAR": {},
    "BAL": {},
    "TRB": {},
    "UNFI": {},
    "SXP": {},
    "WAVES": {},
    "HOT": {},
    "MTL": {},
    "TOMO": {},
    "DENT": {},
    "OGN": {},
    "BTS": {},
    "STMX": {},
    "KNC": {},
    "DGB": {},
    "OCEAN": {},
    "LUNA": {},
    "RSR": {},
    "BZRX": {},
    "BEL": {},
    "HNT": {},
    "ALPHA": {},
    "CTK": {},
    "SKL": {},
    "LIT": {},
    "SFP": {},
    "BTCDOM": {},
    "1000SHIB": {}
  }
}